watch_fs.py
watch_fs-1.5.0.dist-info/WHEEL
watch_fs-1.5.0.dist-info/RECORD
watch_fs-1.5.0.dist-info/DESCRIPTION.rst
watch_fs-1.5.0.dist-info/metadata.json
watch_fs-1.5.0.dist-info/entry_points.txt
watch_fs-1.5.0.dist-info/top_level.txt
watch_fs-1.5.0.dist-info/METADATA
