Metadata-Version: 2.0
Name: watch-fs
Version: 1.5.0
Summary: Run commands when files change
Home-page: https://github.com/borntyping/watch-fs
Author: Sam Clements
Author-email: sam@borntyping.co.uk
License: MIT
Platform: UNKNOWN
Classifier: Development Status :: 5 - Production/Stable
Classifier: Environment :: Console
Classifier: License :: OSI Approved
Classifier: License :: OSI Approved :: MIT License
Classifier: Operating System :: Unix
Classifier: Programming Language :: Python
Classifier: Programming Language :: Python :: 2
Classifier: Programming Language :: Python :: 3
Classifier: Topic :: Software Development :: Build Tools
Classifier: Topic :: Software Development :: Testing
Classifier: Topic :: Utilities
Requires-Dist: click (>=3.3)
Requires-Dist: pyinotify (>=0.9.4)
